litgpt/__init__.py
litgpt/__main__.py
litgpt/adapter.py
litgpt/adapter_v2.py
litgpt/api.py
litgpt/args.py
litgpt/config.py
litgpt/lora.py
litgpt/model.py
litgpt/parser_config.py
litgpt/pretrain.py
litgpt/prompts.py
litgpt/tokenizer.py
litgpt/utils.py
litgpt/chat/__init__.py
litgpt/chat/base.py
litgpt/data/__init__.py
litgpt/data/alpaca.py
litgpt/data/alpaca_2k.py
litgpt/data/alpaca_gpt4.py
litgpt/data/base.py
litgpt/data/deita.py
litgpt/data/flan.py
litgpt/data/json_data.py
litgpt/data/lima.py
litgpt/data/lit_data.py
litgpt/data/longform.py
litgpt/data/microllama.py
litgpt/data/openwebtext.py
litgpt/data/prepare_slimpajama.py
litgpt/data/prepare_starcoder.py
litgpt/data/text_files.py
litgpt/data/tinyllama.py
litgpt/data/tinystories.py
litgpt/deploy/__init__.py
litgpt/deploy/serve.py
litgpt/eval/evaluate.py
litgpt/finetune/__init__.py
litgpt/finetune/adapter.py
litgpt/finetune/adapter_v2.py
litgpt/finetune/full.py
litgpt/finetune/lora.py
litgpt/finetune/lora_legacy.py
litgpt/generate/__init__.py
litgpt/generate/adapter.py
litgpt/generate/adapter_v2.py
litgpt/generate/base.py
litgpt/generate/full.py
litgpt/generate/sequentially.py
litgpt/generate/speculative_decoding.py
litgpt/generate/tp.py
litgpt/scripts/__init__.py
litgpt/scripts/convert_hf_checkpoint.py
litgpt/scripts/convert_lit_checkpoint.py
litgpt/scripts/convert_pretrained_checkpoint.py
litgpt/scripts/download.py
litgpt/scripts/merge_lora.py
litgpt-0.5.12.dist-info/licenses/LICENSE
litgpt-0.5.12.dist-info/METADATA
litgpt-0.5.12.dist-info/WHEEL
litgpt-0.5.12.dist-info/entry_points.txt
litgpt-0.5.12.dist-info/top_level.txt
litgpt-0.5.12.dist-info/RECORD
