Metadata-Version: 2.4
Name: litgpt
Version: 0.5.12
Summary: Hackable implementation of state-of-the-art open-source LLMs
Author-email: Lightning AI <contact@lightning.ai>
License:                                  Apache License
Project-URL: documentation, https://github.com/lightning-AI/litgpt/tutorials
Project-URL: homepage, https://github.com/lightning-AI/litgpt
Classifier: Programming Language :: Python :: 3 :: Only
Classifier: Programming Language :: Python :: 3.10
Classifier: Programming Language :: Python :: 3.11
Classifier: Programming Language :: Python :: 3.12
Classifier: Programming Language :: Python :: 3.13
Requires-Python: >=3.10
License-File: LICENSE
Requires-Dist: huggingface-hub<0.35,>=0.30
Requires-Dist: jsonargparse[signatures]<=4.41,>=4.37; python_version >= "3.10"
Requires-Dist: lightning>=2.5
Requires-Dist: psutil==7.1.3
Requires-Dist: safetensors>=0.4.3
Requires-Dist: tokenizers>=0.21
Requires-Dist: torch>=2.7
Requires-Dist: tqdm>4.66
Provides-Extra: compiler
Requires-Dist: lightning-thunder>=0.2.dev20250119; (python_version >= "3.10" and sys_platform == "linux") and extra == "compiler"
Provides-Extra: extra
Requires-Dist: bitsandbytes<0.43,>=0.42; sys_platform == "darwin" and extra == "extra"
Requires-Dist: bitsandbytes<0.48,>=0.45.2; (sys_platform == "linux" or sys_platform == "win32") and extra == "extra"
Requires-Dist: datasets<4,>=2.18; extra == "extra"
Requires-Dist: huggingface-hub[hf-transfer]>=0.21; extra == "extra"
Requires-Dist: litdata==0.2.51; extra == "extra"
Requires-Dist: litserve>0.2; extra == "extra"
Requires-Dist: lm-eval<0.4.9.1,>=0.4.2; extra == "extra"
Requires-Dist: pandas>=1.9; extra == "extra"
Requires-Dist: pyarrow>=15.0.2; extra == "extra"
Requires-Dist: requests>=2.31; extra == "extra"
Requires-Dist: sentencepiece>=0.2; extra == "extra"
Requires-Dist: tensorboard>=2.14; extra == "extra"
Requires-Dist: torchmetrics>=1.3.1; extra == "extra"
Requires-Dist: transformers<4.57,>=4.51.3; extra == "extra"
Requires-Dist: uvloop>=0.2; sys_platform != "win32" and extra == "extra"
Requires-Dist: zstandard>=0.22; extra == "extra"
Provides-Extra: test
Requires-Dist: einops>=0.7; extra == "test"
Requires-Dist: protobuf>=4.23.4; extra == "test"
Requires-Dist: pytest>=8.1.1; extra == "test"
Requires-Dist: pytest-benchmark>=5.1; extra == "test"
Requires-Dist: pytest-dependency>=0.6; extra == "test"
Requires-Dist: pytest-rerunfailures>=14; extra == "test"
Requires-Dist: pytest-timeout>=2.3.1; extra == "test"
Dynamic: license-file
